{"train": [{"input": [[0, 0, 4, 4, 4, 0, 0, 4, 4, 0, 0, 4, 0]], "output": [[0, 0, 6, 6, 6, 0, 0, 2, 2, 0, 0, 8, 0]]}, {"input": [[0, 4, 4, 4, 0, 0, 0, 4, 4, 0, 4, 0, 0]], "output": [[0, 6, 6, 6, 0, 0, 0, 2, 2, 0, 8, 0, 0]]}, {"input": [[0, 0, 4, 0, 0, 0, 4, 4, 0, 0, 4, 4, 4]], "output": [[0, 0, 8, 0, 0, 0, 2, 2, 0, 0, 6, 6, 6]]}], "test": [{"input": [[0, 0, 4, 4, 0, 0, 0, 4, 4, 4, 0, 0, 0]], "output": [[0, 0, 2, 2, 0, 0, 0, 6, 6, 6, 0, 0, 0]]}], "uuid": "-7418070649508532291-2455385795606612612"}