{"train": [{"input": [[0, 0, 3, 3, 3, 3, 3, 3, 3, 0, 3, 3, 3, 3, 3, 3, 0, 0, 0, 0]], "output": [[0, 0, 9, 9, 9, 9, 9, 9, 9, 0, 3, 3, 3, 3, 3, 3, 0, 0, 0, 0]]}, {"input": [[0, 0, 0, 3, 3, 3, 3, 0, 3, 0, 0, 0, 3, 3, 3, 0, 0, 3, 3, 0]], "output": [[0, 0, 0, 9, 9, 9, 9, 0, 3, 0, 0, 0, 3, 3, 3, 0, 0, 3, 3, 0]]}, {"input": [[0, 3, 3, 3, 3, 3, 0, 3, 3, 0, 3, 0, 0, 3, 3, 3, 0, 0, 3, 0]], "output": [[0, 9, 9, 9, 9, 9, 0, 3, 3, 0, 3, 0, 0, 3, 3, 3, 0, 0, 3, 0]]}], "test": [{"input": [[0, 0, 3, 3, 3, 3, 0, 0, 3, 3, 0, 3, 0, 0, 3, 3, 3, 0, 0, 0]], "output": [[0, 0, 9, 9, 9, 9, 0, 0, 3, 3, 0, 3, 0, 0, 3, 3, 3, 0, 0, 0]]}], "uuid": "-6463894762582976749-2419749881867002685"}