{"train": [{"input": [[1, 1, 5, 6, 8], [0, 1, 5, 6, 6], [5, 5, 5, 5, 5], [7, 7, 5, 4, 4], [7, 7, 5, 0, 4]], "output": [[1, 6, 0, 0, 0], [7, 4, 0, 0, 0], [0, 0, 0, 0, 0], [0, 0, 0, 0, 0], [0, 0, 0, 0, 0]]}, {"input": [[7, 7, 5, 7, 7], [7, 7, 5, 7, 7], [5, 5, 5, 5, 5], [7, 7, 5, 7, 7], [7, 7, 5, 7, 7]], "output": [[7, 7, 0, 0, 0], [7, 7, 0, 0, 0], [0, 0, 0, 0, 0], [0, 0, 0, 0, 0], [0, 0, 0, 0, 0]]}, {"input": [[6, 6, 5, 8, 6], [0, 6, 5, 8, 4], [5, 5, 5, 5, 5], [3, 3, 5, 2, 2], [3, 3, 5, 3, 2]], "output": [[6, 8, 0, 0, 0], [3, 2, 0, 0, 0], [0, 0, 0, 0, 0], [0, 0, 0, 0, 0], [0, 0, 0, 0, 0]]}], "test": [{"input": [[3, 2, 5, 6, 6], [3, 4, 5, 8, 6], [5, 5, 5, 5, 5], [7, 7, 5, 5, 5], [3, 7, 5, 0, 8]], "output": [[3, 6, 0, 0, 0], [7, 5, 0, 0, 0], [0, 0, 0, 0, 0], [0, 0, 0, 0, 0], [0, 0, 0, 0, 0]]}]}